graniteloom/__init__.py
graniteloom/__main__.py
graniteloom-0.2.0.dist-info/METADATA
graniteloom-0.2.0.dist-info/WHEEL
graniteloom-0.2.0.dist-info/licenses/LICENSE
graniteloom-0.2.0.dist-info/RECORD
