Metadata-Version: 2.1
Name: graniteloom
Version: 0.2.0
Summary: Auth Token based easy repo cloning
Project-URL: Homepage, https://github.com/ironloom/granite
Project-URL: Issues, https://github.com/ironloom/granite/issues
Author-email: zewenn <ironloomeu@gamil.com>
License-File: LICENSE
Classifier: License :: OSI Approved :: MIT License
Classifier: Operating System :: OS Independent
Classifier: Programming Language :: Python :: 3
Requires-Python: >=3.7
